givememoneypastaga/__init__.py
givememoneypastaga/main.py
givememoneypastaga-0.1.0.dist-info/METADATA
givememoneypastaga-0.1.0.dist-info/WHEEL
givememoneypastaga-0.1.0.dist-info/RECORD
